noa_tools/__init__.py
noa_tools/general_utils.py
noa_tools/hook_utils.py
noa_tools/query_api.py
noa_tools/rendering.py
noa_tools/s3_utils.py
noa_tools/seriation_utils.py
noa_tools-0.1.1.post1.dist-info/METADATA
noa_tools-0.1.1.post1.dist-info/WHEEL
noa_tools-0.1.1.post1.dist-info/RECORD
