Metadata-Version: 2.1
Name: noa_tools
Version: 0.1.1.post1
Summary: 
Author: Noa Nabeshima
Author-email: noanabeshima@gmail.com
Requires-Python: >=3.10,<4.0
Classifier: Programming Language :: Python :: 3
Classifier: Programming Language :: Python :: 3.10
Classifier: Programming Language :: Python :: 3.11
Classifier: Programming Language :: Python :: 3.12
Requires-Dist: boto3 (>=1.34.138,<2.0.0)
Requires-Dist: einops (>=0.8.0,<0.9.0)
Requires-Dist: matplotlib (>=3.9.0,<4.0.0)
Requires-Dist: openai (>=1.35.9,<2.0.0)
Requires-Dist: pillow (>=10.4.0,<11.0.0)
Requires-Dist: plotly (>=5.23.0,<6.0.0)
Requires-Dist: scipy (>=1.14.0,<2.0.0)
Requires-Dist: tsp-solver (>=0.1,<0.2)
